{"cameraMode":{"drawMode":0,"name":"Shaded","section":"Shading Mode"},"sceneLighting":true,"audioPlay":false,"sceneViewState":{"m_AlwaysRefresh":false,"showFog":true,"showSkybox":true,"showFlares":true,"showImageEffects":true,"showParticleSystems":true,"showVisualEffectGraphs":true,"m_FxEnabled":true},"in2DMode":false,"pivot":{"x":951.1968994140625,"y":563.0192260742188,"z":-1.434814453125},"rotation":{"x":0.028184685856103898,"y":0.008095607161521912,"z":0.00024453294463455677,"w":-0.9995474815368652},"size":663.7481689453125,"orthographic":false}