{"cameraMode":{"drawMode":0,"name":"Shaded","section":"Shading Mode"},"sceneLighting":false,"audioPlay":false,"sceneViewState":{"m_AlwaysRefresh":false,"showFog":true,"showSkybox":false,"showFlares":true,"showImageEffects":true,"showParticleSystems":true,"showVisualEffectGraphs":true,"m_FxEnabled":true},"in2DMode":false,"pivot":{"x":720.5,"y":265.0,"z":0.0},"rotation":{"x":-0.18155241012573243,"y":0.15184757113456727,"z":-0.028370099142193795,"w":-0.9711498618125916},"size":206.15528869628907,"orthographic":false}